{
  "id": "dancing-spokes",
  "titleShort": "Web Doodle:\nDancing\nSpokes",
  "titleLong": "Dancing Spokes",
  "url": "http://jackieandlevi.com/dancing-spokes",
  "repositoryUrl": "https://github.com/levisl176/dancing-spokes",
  "jobTitle": "",
  "date": "2014",
  "categories": [
    "side-project",
    "web",
    "front-end",
    "svg",
    "doodle",
    "tiny",
    "animation"
  ],
  "images": [
    {
      "fileName": "",
      "description": ""
    },
    {
      "fileName": "",
      "description": ""
    },
    {
      "fileName": "",
      "description": ""
    }
  ],
  "videos": [],
  "content": ""
}