{
  "id": "idean",
  "titleShort": "Idean",
  "titleLong": "Idean",
  "emphasis": 0.7,
  "color": "#e23000",
  "urls": {
    "homepage": "http://idean.com"
  },
  "jobTitle": "UI Developer",
  "location": "Palo Alto, CA",
  "date": {
    "start": "3/2014",
    "end": "3/2015"
  },
  "categories": [
    "Work",
    "Web",
    "Frontend",
    "Back-End",
    "User-Experience",
    "MEAN-Stack",
    "Angular",
    "node.js",
    "MongoDB",
    "Express",
    "gulp.js",
    "Grunt",
    "d3.js",
    "SVG",
    "PHP",
    "Teamwork"
  ],
  "images": [
    {
      "fileName": "idean-hawaii.jpg",
      "description": "Hawaii!! Idean flew their employees to Oahu for their annual retreat."
    },
    {
      "fileName": "palo-alto-studio.jpg",
      "description": "Idean's office at their head quarters in Palo Alto. The home-like atmosphere of the house definitely reflects the friendly and relaxed atmosphere of the company as a whole."
    },
    {
      "fileName": "idean-definition.png",
      "description": "Life's too short for crappy UX!"
    }
  ],
  "videos": [
    {
      "videoHost": "vimeo",
      "id": "50565896",
      "description": "Idean's introductory video: why a good user experience is important and how Idean can help."
    },
    {
      "videoHost": "vimeo",
      "id": "88468432",
      "description": "Idean's UX Rap!"
    }
  ],
  "content": ""
}