{
  "id": "progress-circle",
  "titleShort": "Web Doodle:\nProgress\nCircle",
  "titleLong": "Progress Circle",
  "urls": {
    "demo": "https://levi.dev/progress-circle",
    "github": "https://github.com/levilindsey/progress-circle",
    "codepen": "http://codepen.io/levisl176/pen/ndklu"
  },
  "jobTitle": "",
  "location": "",
  "date": "2/2014",
  "categories": [
    "side-project",
    "web",
    "doodle",
    "frontend",
    "svg",
    "tiny",
    "animation"
  ],
  "images": [
    {
      "fileName": "screenshot1.png",
      "description": "The progress circle with its larger radius. The dots revolve in a clockwise direction while the colors of the dots transition in such a way to make the colors appear to transition in a counter-clockwise direction."
    },
    {
      "fileName": "screenshot2.png",
      "description": "The progress circle with its smaller radius. The lightness increases as the radius decreases."
    }
  ],
  "videos": [],
  "content": ""
}